<?xml version="1.0"?>
<response><status>OK</status><result><item0><masterclass>Food &amp; Beverages</masterclass><class>Food Stall</class><subclass></subclass><name>Pusat Jajanan Kuliner Pondok Delima</name><longitude>106.859</longitude><latitude>-6.30071</latitude><province>DKI JAKARTA</province><district>JAKARTA TIMUR</district><subdistrict>PASARREBO</subdistrict><village>GEDONG</village><address>JL. Raya Tengah, No. 9 A, Pasar Rebo</address><telephone>21 8779 7687</telephone><fax></fax><email></email><website></website><imagelink></imagelink></item0><item1><masterclass>Food &amp; Beverages</masterclass><class>Food Stall</class><subclass></subclass><name>Kuliner 82</name><longitude>106.863</longitude><latitude>-6.19259</latitude><province>DKI JAKARTA</province><district>JAKARTA PUSAT</district><subdistrict>CEMPAKA PUTIH</subdistrict><village>RAWA SARI</village><address>JL. Pramuka, Jakarta</address><telephone>21 9145 1957, 0881 6171 265</telephone><fax></fax><email></email><website></website><imagelink></imagelink></item1><item2><masterclass>Food &amp; Beverages</masterclass><class>Food Stall</class><subclass></subclass><name>Asiana Kuliner</name><longitude>106.792</longitude><latitude>-6.23323</latitude><province>DKI JAKARTA</province><district>JAKARTA SELATAN</district><subdistrict>KEBAYORAN BARU</subdistrict><village>GUNUNG</village><address>JL. Martimbang 2, Jakarta</address><telephone>21 7032 3660</telephone><fax>021 7236 661</fax><email></email><website></website><imagelink></imagelink></item2><item3><masterclass>Food &amp; Beverages</masterclass><class>Food Stall</class><subclass></subclass><name>Sop Buah Segar Pak Schubi</name><longitude>106.845</longitude><latitude>-6.26729</latitude><province>DKI JAKARTA</province><district>JAKARTA SELATAN</district><subdistrict>PASAR MINGGU</subdistrict><village>PEJATEN TIMUR</village><address>Bilast Park - Kuliner Malam Unit Ia, JL. Raya Pasar Minggu, No. 9, Jakarta</address><telephone>21 7919 3514</telephone><fax></fax><email></email><website></website><imagelink></imagelink></item3><item4><masterclass>Food &amp; Beverages</masterclass><class>Restaurant</class><subclass></subclass><name>Depot K 7</name><longitude>106.911</longitude><latitude>-6.24747</latitude><province>DKI JAKARTA</province><district>JAKARTA TIMUR</district><subdistrict>DUREN SAWIT</subdistrict><village>DUREN SAWIT</village><address>JL. Kalimalang, Duren Sawit, Taman Kuliner, Jakarta</address><telephone>21 8600 058</telephone><fax></fax><email></email><website></website><imagelink></imagelink></item4><item5><masterclass>Business</masterclass><class>Private Company</class><subclass></subclass><name>Pariwisata &amp; Hiburan/Wisata Kuliner/Fast Food. PT</name><longitude>106.834</longitude><latitude>-6.16364</latitude><province>DKI JAKARTA</province><district>JAKARTA PUSAT</district><subdistrict>SAWAH BESAR</subdistrict><village>PASAR BARU</village><address>JL. Pasar Baru, No. 115, Jakarta</address><telephone>21 650 6469</telephone><fax></fax><email></email><website></website><imagelink></imagelink></item5><item6><masterclass>Business</masterclass><class>Private Company</class><subclass></subclass><name>Pariwisata &amp; Hiburan/Wisata Kuliner/Fast Food. PT</name><longitude>106.823</longitude><latitude>-6.18909</latitude><province>DKI JAKARTA</province><district>JAKARTA PUSAT</district><subdistrict>MENTENG</subdistrict><village>GONDANGDIA</village><address>JL. Muhammad Husni Thamrin, No. 9, Jakarta</address><telephone>21 345 7225</telephone><fax></fax><email></email><website></website><imagelink></imagelink></item6><item7><masterclass>Business</masterclass><class>Private Company</class><subclass></subclass><name>Pariwisata &amp; Hiburan/Wisata Kuliner/Fast Food. PT</name><longitude>106.839</longitude><latitude>-6.16496</latitude><province>DKI JAKARTA</province><district>JAKARTA PUSAT</district><subdistrict>KEMAYORAN</subdistrict><village>GUNUNG SAHARI SELATAN</village><address>JL. Gunung Sahari, No. 59, Jakarta</address><telephone>21 560 6056</telephone><fax></fax><email></email><website></website><imagelink></imagelink></item7><item8><masterclass>Food &amp; Beverages</masterclass><class>Bakery</class><subclass></subclass><name>Waroeng Croissant</name><longitude>106.846</longitude><latitude>-6.27441</latitude><province>DKI JAKARTA</province><district>JAKARTA SELATAN</district><subdistrict>PASAR MINGGU</subdistrict><village>PEJATEN BARAT</village><address>JL. Raya Pasar Minggu No. 9Pancoran - South Jakarta  Bilast Park - Kuliner Malam Unit 14</address><telephone>62 21 7919 3514</telephone><fax></fax><email></email><website></website><imagelink></imagelink></item8><item9><masterclass>Food &amp; Beverages</masterclass><class>Restaurant</class><subclass></subclass><name>basil &amp; co</name><longitude>106.917</longitude><latitude>-6.24775</latitude><province>DKI JAKARTA</province><district>JAKARTA TIMUR</district><subdistrict>DUREN SAWIT</subdistrict><village>DUREN SAWIT</village><address>JL.Raya Kalimalang Kav 22 (Taman Kuliner) Duren Sawit East Jakarta 13440</address><telephone>62 21 9346 1965</telephone><fax></fax><email></email><website></website><imagelink></imagelink></item9><item10><masterclass>Food &amp; Beverages</masterclass><class>Restaurant</class><subclass></subclass><name>Bang Dibul</name><longitude>106.935</longitude><latitude>-6.2486</latitude><province>DKI JAKARTA</province><district>JAKARTA TIMUR</district><subdistrict>DUREN SAWIT</subdistrict><village>PONDOK KELAPA</village><address>Saung Blessing (Saung Kuliner) JL. Raya Kalimalang, Lampiri &#x2013; East Jakarta 13440</address><telephone>62 21 3319 3035, +62 21 3319 3036</telephone><fax></fax><email></email><website></website><imagelink>/Restaurant/id256608-bang-dibul.jpg</imagelink></item10><item11><masterclass>Food &amp; Beverages</masterclass><class>Restaurant</class><subclass></subclass><name>Pojok Kuliner</name><longitude>106.829</longitude><latitude>-6.254</latitude><province>DKI JAKARTA</province><district>JAKARTA SELATAN</district><subdistrict>PANCORAN</subdistrict><village>DUREN TIGA</village><address>JL. Duren Tiga, No. 6 A, Jakarta</address><telephone>21 794 2462</telephone><fax></fax><email></email><website></website><imagelink>/Restaurant/id680295-pojok-kuliner.jpg</imagelink></item11><item12><masterclass>Food &amp; Beverages</masterclass><class>Restaurant</class><subclass></subclass><name>Trenz Kuliner</name><longitude>106.794</longitude><latitude>-6.30913</latitude><province>DKI JAKARTA</province><district>JAKARTA SELATAN</district><subdistrict>CILANDAK</subdistrict><village>PONDOK LABU</village><address>JL. RS. Fatmawati, RT. 03/ RW. 10 No. 10, Pondok Labu, Jakarta</address><telephone>, 0818 0814 9554</telephone><fax></fax><email></email><website></website><imagelink>/Restaurant/id1684696-trenz-kuliner.jpg</imagelink></item12><item13><masterclass>Food &amp; Beverages</masterclass><class>Restaurant</class><subclass></subclass><name>Ahlinye Kuliner</name><longitude>106.833</longitude><latitude>-6.18322</latitude><province>DKI JAKARTA</province><district>JAKARTA PUSAT</district><subdistrict>MENTENG</subdistrict><village>KEBON SIRIH</village><address>JL. Menteng, Jakarta, 10310</address><telephone>21 3190 6272, 0856 9190 1099</telephone><fax></fax><email></email><website>http://www.kuliner.ahlinye.com</website><imagelink></imagelink></item13><item14><masterclass>Food &amp; Beverages</masterclass><class>Restaurant</class><subclass></subclass><name>Madinah Kuliner Betawi</name><longitude>106.859</longitude><latitude>-6.30714</latitude><province>DKI JAKARTA</province><district>JAKARTA TIMUR</district><subdistrict>PASARREBO</subdistrict><village>GEDONG</village><address>JL. Kesehatan, Cijantung, Jakarta</address><telephone>21 9845 0491</telephone><fax></fax><email></email><website></website><imagelink></imagelink></item14><item15><masterclass>Food &amp; Beverages</masterclass><class>Food Stall</class><subclass></subclass><name>Pempek Palembang &amp;quot;Serasan - Sekal&amp;quot;</name><longitude>106.843</longitude><latitude>-6.24816</latitude><province>DKI JAKARTA</province><district>JAKARTA SELATAN</district><subdistrict>PANCORAN</subdistrict><village>PANCORAN</village><address>Bilast Park Kuliner Malam, JL. Raya Pasar Minggu, Unit I - B, Jakarta, 12780</address><telephone>21 7919 3514</telephone><fax></fax><email></email><website></website><imagelink></imagelink></item15><item16><masterclass>Food &amp; Beverages</masterclass><class>Food Stall</class><subclass></subclass><name>Rumah Makan Sunda Kuliner Bandung</name><longitude>106.832</longitude><latitude>-6.18504</latitude><province>DKI JAKARTA</province><district>JAKARTA PUSAT</district><subdistrict>MENTENG</subdistrict><village>KEBON SIRIH</village><address>JL. Wahid Hasyim, No. 16, Jakarta</address><telephone>21 390 2882</telephone><fax></fax><email></email><website></website><imagelink></imagelink></item16><item17><masterclass>Food &amp; Beverages</masterclass><class>Food Stall</class><subclass></subclass><name>Pondok Ikan Ibu Jayanti</name><longitude>106.846</longitude><latitude>-6.27384</latitude><province>DKI JAKARTA</province><district>JAKARTA SELATAN</district><subdistrict>PASAR MINGGU</subdistrict><village>PEJATEN BARAT</village><address>JL. Raya Pasar Minggu, No. 9, Pancoran, Bilast Park - Kuliner Malam Unit 5, Jakarta</address><telephone>21 7919 3514</telephone><fax></fax><email></email><website></website><imagelink></imagelink></item17><item18><masterclass>Food &amp; Beverages</masterclass><class>Food Stall</class><subclass></subclass><name>Bakmi Jogja Jape Methe</name><longitude>106.824</longitude><latitude>-6.23986</latitude><province>DKI JAKARTA</province><district>JAKARTA SELATAN</district><subdistrict>MAMPANG PRAPATAN</subdistrict><village>KUNINGAN BARAT</village><address>Kuliner Center Point, JL. Kapten Pierre Tendean, Mampang, Jakarta</address><telephone>21 9407 5729</telephone><fax></fax><email></email><website></website><imagelink></imagelink></item18><item19><masterclass>Food &amp; Beverages</masterclass><class>Restaurant</class><subclass></subclass><name>Pondok Bebek Ibu Jayanti</name><longitude>106.845</longitude><latitude>-6.28036</latitude><province>DKI JAKARTA</province><district>JAKARTA SELATAN</district><subdistrict>PASAR MINGGU</subdistrict><village>PASAR MINGGU</village><address>Bilast Park Kuliner Malam Unit 6, JL. Raya Pasar Minggu, No. 9, Jakarta</address><telephone>21 7919 3514</telephone><fax></fax><email></email><website></website><imagelink></imagelink></item19><item20><masterclass>Food &amp; Beverages</masterclass><class>Restaurant</class><subclass></subclass><name>Ayam Bakar Bu Sam</name><longitude>106.845</longitude><latitude>-6.2768</latitude><province>DKI JAKARTA</province><district>JAKARTA SELATAN</district><subdistrict>PASAR MINGGU</subdistrict><village>PEJATEN BARAT</village><address>Bilast Park Kuliner Malam Unit 2, JL. Raya Pasar Minggu, No. 9, Jakarta</address><telephone>21 7919 3514</telephone><fax></fax><email></email><website></website><imagelink></imagelink></item20><item21><masterclass>Food &amp; Beverages</masterclass><class>Restaurant</class><subclass></subclass><name>Rumah Mie</name><longitude>106.845</longitude><latitude>-6.27678</latitude><province>DKI JAKARTA</province><district>JAKARTA SELATAN</district><subdistrict>PASAR MINGGU</subdistrict><village>PEJATEN BARAT</village><address>Bilast Park - Kuliner Malam Unit 7, JL. Raya Pasar Minggu, No. 9, Jakarta</address><telephone>21 7919 3514</telephone><fax></fax><email></email><website></website><imagelink></imagelink></item21><item22><masterclass>Food &amp; Beverages</masterclass><class>Restaurant</class><subclass></subclass><name>Cafe Humor RR</name><longitude>106.845</longitude><latitude>-6.27674</latitude><province>DKI JAKARTA</province><district>JAKARTA SELATAN</district><subdistrict>PASAR MINGGU</subdistrict><village>PEJATEN BARAT</village><address>Bilast Park - Kuliner Malam Unit 8, JL. Raya Pasar Minggu, No. 9, Jakarta</address><telephone>21 7919 3514, 089 9923 3338</telephone><fax></fax><email></email><website></website><imagelink></imagelink></item22><item23><masterclass>Food &amp; Beverages</masterclass><class>Bakery</class><subclass></subclass><name>Roti Bakar Pancoran</name><longitude>106.847</longitude><latitude>-6.27132</latitude><province>DKI JAKARTA</province><district>JAKARTA SELATAN</district><subdistrict>PASAR MINGGU</subdistrict><village>PEJATEN TIMUR</village><address>Bilast Park - Kuliner Malam Unit 3, JL. Raya Pasar Minggu, No. 9, Jakarta</address><telephone>21 7919 3514</telephone><fax></fax><email></email><website></website><imagelink></imagelink></item23><item24><masterclass>Food &amp; Beverages</masterclass><class>Restaurant</class><subclass></subclass><name>Taman Kuliner</name><longitude>106.895</longitude><latitude>-6.24001</latitude><province>DKI JAKARTA</province><district>JAKARTA TIMUR</district><subdistrict>DUREN SAWIT</subdistrict><village>PONDOK BAMBU</village><address>JL. Raya Kalimalang, Jakarta</address><telephone>21 8600 058</telephone><fax></fax><email></email><website></website><imagelink></imagelink></item24><item25><masterclass>Food &amp; Beverages</masterclass><class>Food Stall</class><subclass></subclass><name>Warung Demang Betawi Kuliner</name><longitude>106.752</longitude><latitude>-6.21712</latitude><province>DKI JAKARTA</province><district>JAKARTA BARAT</district><subdistrict>KEMBANGAN</subdistrict><village>JOGLO</village><address>JL. Joglo Raya, No. 46 A, Jakarta</address><telephone>21 5890 5807, 021 3298 0839</telephone><fax></fax><email></email><website></website><imagelink></imagelink></item25><item26><masterclass>Food &amp; Beverages</masterclass><class>Restaurant</class><subclass></subclass><name>MU 98</name><longitude>106.826</longitude><latitude>-6.16433</latitude><province>DKI JAKARTA</province><district>JAKARTA PUSAT</district><subdistrict>GAMBIR</subdistrict><village>KEBON KELAPA</village><address>JL. Pecenongan Raya, Wisata Malam Kuliner Pecenongan, Jakarta, 10120</address><telephone>857 7278 8338</telephone><fax></fax><email></email><website></website><imagelink></imagelink></item26><item27><masterclass>Education</masterclass><class>Course / Other School</class><subclass></subclass><name>Yayasan Gizi Kuliner</name><longitude>106.792</longitude><latitude>-6.24406</latitude><province>DKI JAKARTA</province><district>JAKARTA SELATAN</district><subdistrict>KEBAYORAN BARU</subdistrict><village>KRAMAT PELA</village><address>JL. Langsat 1, No. 2, Jakarta</address><telephone>21 726 2833</telephone><fax></fax><email></email><website></website><imagelink></imagelink></item27><item28><masterclass>Commercial</masterclass><class>Agen Koran &amp; Majalah</class><subclass></subclass><name>Tabloid Kuliner</name><longitude>106.798</longitude><latitude>-6.26502</latitude><province>DKI JAKARTA</province><district>JAKARTA SELATAN</district><subdistrict>KEBAYORAN BARU</subdistrict><village>CIPETE UTARA</village><address>JL. RS Fatmawati, No.15, Komplek Golden Plaza (D&#x2019;dest) Blok D 1-2, Jakarta</address><telephone>21 750 7850</telephone><fax>021 751 2695</fax><email></email><website></website><imagelink></imagelink></item28><item29><masterclass>Food &amp; Beverages</masterclass><class>Restaurant</class><subclass></subclass><name>Taman Kuliner Kalibata</name><longitude>106.847</longitude><latitude>-6.25538</latitude><province>DKI JAKARTA</province><district>JAKARTA SELATAN</district><subdistrict>PANCORAN</subdistrict><village>DUREN TIGA</village><address></address><telephone></telephone><fax></fax><email></email><website></website><imagelink></imagelink></item29><item30><masterclass>Food &amp; Beverages</masterclass><class>Restaurant</class><subclass></subclass><name>Shabu Street</name><longitude>106.826742</longitude><latitude>-6.162124</latitude><province>DKI JAKARTA</province><district>JAKARTA PUSAT</district><subdistrict>GAMBIR</subdistrict><village>KEBON KELAPA</village><address>Wisata Kuliner Pecenongan
Jl. Pecenongan Raya (Near Red Top Hotel), Jakarta</address><telephone></telephone><fax></fax><email></email><website></website><imagelink></imagelink></item30><item31><masterclass>Food &amp; Beverages</masterclass><class>Restaurant</class><subclass></subclass><name>Wisata Kuliner Pecenongan</name><longitude>106.826751</longitude><latitude>-6.161962</latitude><province>DKI JAKARTA</province><district>JAKARTA PUSAT</district><subdistrict>GAMBIR</subdistrict><village>KEBON KELAPA</village><address>Jl. KH. Samanhudi, Sawah Besar</address><telephone></telephone><fax></fax><email></email><website></website><imagelink></imagelink></item31><item32><masterclass>Food &amp; Beverages</masterclass><class>Restaurant</class><subclass></subclass><name>Kuliner</name><longitude>106.80679</longitude><latitude>-6.239236</latitude><province>DKI JAKARTA</province><district>JAKARTA SELATAN</district><subdistrict>KEBAYORAN BARU</subdistrict><village>SELONG</village><address>Jl. Wolter Mongonsidi No. 19 Kebayoran Baru, Jakarta Selatan</address><telephone></telephone><fax></fax><email></email><website></website><imagelink></imagelink></item32><item33><masterclass>Food &amp; Beverages</masterclass><class>Restaurant</class><subclass></subclass><name>Basil &amp; Co</name><longitude>106.91313</longitude><latitude>-6.228595</latitude><province>DKI JAKARTA</province><district>JAKARTA TIMUR</district><subdistrict>DUREN SAWIT</subdistrict><village>DUREN SAWIT</village><address>Taman Kuliner
Jl. Raya Kalimalang Kav 22
Duren Sawit, Jakarta</address><telephone></telephone><fax></fax><email></email><website></website><imagelink></imagelink></item33><item34><masterclass>Food &amp; Beverages</masterclass><class>Food Stall</class><subclass></subclass><name>Warung Demang Betawi Kuliner</name><longitude>106.738517</longitude><latitude>-6.220248</latitude><province>DKI JAKARTA</province><district>JAKARTA BARAT</district><subdistrict>KEMBANGAN</subdistrict><village>JOGLO</village><address>Jl. Joglo Raya No. 46, Kembangan</address><telephone></telephone><fax></fax><email></email><website></website><imagelink></imagelink></item34><item35><masterclass>Food &amp; Beverages</masterclass><class>Restaurant</class><subclass></subclass><name>Kuliner</name><longitude>106.853238</longitude><latitude>-6.185702</latitude><province>DKI JAKARTA</province><district>JAKARTA PUSAT</district><subdistrict>JOHAR BARU</subdistrict><village>JOHAR BARU</village><address>Kramat Sentiong 5/187E</address><telephone></telephone><fax></fax><email></email><website></website><imagelink></imagelink></item35><item36><masterclass>Food &amp; Beverages</masterclass><class>Food Stall</class><subclass></subclass><name>RM Sunda Kuliner Bandung</name><longitude>106.83274</longitude><latitude>-6.18489</latitude><province>DKI JAKARTA</province><district>JAKARTA PUSAT</district><subdistrict>MENTENG</subdistrict><village>KEBON SIRIH</village><address>Jl. KH. Wahid Hasyim No. 16</address><telephone></telephone><fax></fax><email></email><website></website><imagelink></imagelink></item36><item37><masterclass>Food &amp; Beverages</masterclass><class>Restaurant</class><subclass></subclass><name>Wisata Kuliner Malam Pecenongan</name><longitude>106.826438</longitude><latitude>-6.167019</latitude><province>DKI JAKARTA</province><district>JAKARTA PUSAT</district><subdistrict>GAMBIR</subdistrict><village>KEBON KELAPA</village><address>Jl. Juanda</address><telephone></telephone><fax></fax><email></email><website></website><imagelink></imagelink></item37><item38><masterclass>Food &amp; Beverages</masterclass><class>Restaurant</class><subclass></subclass><name>Kemiri Sentra Kuliner Indonesia</name><longitude>106.845904</longitude><latitude>-6.274495</latitude><province>DKI JAKARTA</province><district>JAKARTA SELATAN</district><subdistrict>PASAR MINGGU</subdistrict><village>PEJATEN BARAT</village><address>Pejaten Village 3rd floor, Jl. Pejaten Raya, Pasar Minggu</address><telephone></telephone><fax></fax><email></email><website></website><imagelink></imagelink></item38><item39><masterclass>Food &amp; Beverages</masterclass><class>Restaurant</class><subclass></subclass><name>Pablo Mexican Food Kalibata City</name><longitude>106.856439</longitude><latitude>-6.256986</latitude><province>DKI JAKARTA</province><district>JAKARTA SELATAN</district><subdistrict>PANCORAN</subdistrict><village>RAWAJATI</village><address>Kalibata City, Teras Kuliner
Jl. Kalibata Raya No. 1, Jakarta</address><telephone></telephone><fax></fax><email></email><website></website><imagelink></imagelink></item39><item40><masterclass>Food &amp; Beverages</masterclass><class>Restaurant</class><subclass></subclass><name>Bengkel Kuliner</name><longitude>106.909217</longitude><latitude>-6.252162</latitude><province>DKI JAKARTA</province><district>JAKARTA TIMUR</district><subdistrict>MAKASAR</subdistrict><village>CIPINANG MELAYU</village><address>Jl. Raya Jatiwaringin No. 23</address><telephone></telephone><fax></fax><email></email><website></website><imagelink></imagelink></item40><item41><masterclass>Food &amp; Beverages</masterclass><class>Restaurant</class><subclass></subclass><name>Bebek Kuliner Fatmawati</name><longitude>106.796867</longitude><latitude>-6.259233</latitude><province>DKI JAKARTA</province><district>JAKARTA SELATAN</district><subdistrict>KEBAYORAN BARU</subdistrict><village>CIPETE UTARA</village><address>Jl. Fatmawati Raya No. 88A  Kebayoran Baru</address><telephone></telephone><fax></fax><email></email><website></website><imagelink></imagelink></item41></result></response>
 